KARLOM_v1/KARLOM_v1.py
KARLOM_v1/Logicky_simulator.py
KARLOM_v1/McCluskey.py
KARLOM_v1/Soubor.py
KARLOM_v1/Uceni.py
KARLOM_v1/__init__.py
KARLOM_v1/kar_map.py
KARLOM_v1/images/Novy_obvod.png
KARLOM_v1/images/Otevrit.png
KARLOM_v1/images/Rezim_simulace.png
KARLOM_v1/images/Rezim_tvoreni.jpg
KARLOM_v1/images/Ulozit.png
karlom_v1-1.0.0.dist-info/METADATA
karlom_v1-1.0.0.dist-info/WHEEL
karlom_v1-1.0.0.dist-info/entry_points.txt
karlom_v1-1.0.0.dist-info/top_level.txt
karlom_v1-1.0.0.dist-info/RECORD
