Metadata-Version: 2.4
Name: KARLOM_v1
Version: 1.0.0
Summary: Grafický logický simulátor a minimalizátor logických funkcí
Author: Tvé jméno
Classifier: Programming Language :: Python :: 3
Classifier: Operating System :: OS Independent
Requires-Python: >=3.6
Requires-Dist: Pillow
Dynamic: author
Dynamic: classifier
Dynamic: requires-dist
Dynamic: requires-python
Dynamic: summary
